CVor/CVor.py
CVor/__init__.py
CVor-0.0.7.dist-info/LICENSE
CVor-0.0.7.dist-info/METADATA
CVor-0.0.7.dist-info/WHEEL
CVor-0.0.7.dist-info/top_level.txt
CVor-0.0.7.dist-info/RECORD
