Metadata-Version: 2.1
Name: CVor
Version: 0.0.7
Summary: A simple implementation of control variates operator (CVor)
Home-page: https://github.com/uglyghost/CVOR.git
Author: chenxingyan94
Author-email: xychen@swufe.edu.cn
Classifier: Programming Language :: Python :: 3
Classifier: License :: OSI Approved :: MIT License
Classifier: Operating System :: OS Independent
License-File: LICENSE
Requires-Dist: torch
Requires-Dist: torchvision
